formalpdf/__init__.py
formalpdf/fdf.py
formalpdf/utils.py
formalpdf/widget.py
formalpdf-0.1.6.dist-info/METADATA
formalpdf-0.1.6.dist-info/WHEEL
formalpdf-0.1.6.dist-info/licenses/LICENSE
formalpdf-0.1.6.dist-info/RECORD
