Metadata-Version: 2.4
Name: formalpdf
Version: 0.1.6
Summary: An Apache-licensed package for extracting, creating, filling, and flattening PDF Forms.
License-File: LICENSE
Requires-Python: >=3.9
Requires-Dist: pillow>=11.3.0
Requires-Dist: pypdfium2>=4.30
